x7/__init__.py
x7/testing/__init__.py
x7/testing/__version__.py
x7/testing/extended.py
x7/testing/needs_test.py
x7/testing/shell_tools.py
x7/testing/support.py
x7/testing/maketests/__init__.py
x7/testing/maketests/__main__.py
x7/testing/maketests/gen_code.py
x7/testing/maketests/maketests.py
x7/testing/maketests/mod_support.py
x7/testing/maketests/outmap.py
x7/testing/maketests/parse.py
x7/testing/maketests/types.py
x7_testing-0.6.0.dist-info/LICENSE
x7_testing-0.6.0.dist-info/METADATA
x7_testing-0.6.0.dist-info/WHEEL
x7_testing-0.6.0.dist-info/top_level.txt
x7_testing-0.6.0.dist-info/RECORD
